{
  "@context": [
    "http://www.w3.org/ns/anno.jsonld",
    "http://iiif.io/api/presentation/3/context.json"
  ],
  "id": "https://edh.ub.uni-heidelberg.de/iiif/edh/HD004441.manifest.json",
  "type": "Manifest",
  "label": {
    "true": [
      "EDH Image HD004441"
    ]
  },
  "metadata": [
    {
      "label": {
        "true": [
          "Provinz / Italische Region"
        ]
      },
      "value": {
        "true": [
          "Raetia"
        ]
      }
    },
    {
      "label": {
        "true": [
          "Land"
        ]
      },
      "value": {
        "true": [
          "Germany"
        ]
      }
    },
    {
      "label": {
        "true": [
          "Fundort antik"
        ]
      },
      "value": {
        "true": [
          "Augusta Vindelicorum"
        ]
      }
    },
    {
      "label": {
        "true": [
          "Fundort modern"
        ]
      },
      "value": {
        "true": [
          "Augsburg"
        ]
      }
    },
    {
      "label": {
        "true": [
          "Aufbewahrung"
        ]
      },
      "value": {
        "true": [
          "Augsburg, Maximilianmus."
        ]
      }
    },
    {
      "label": {
        "true": [
          true
        ]
      },
      "value": {
        "true": [
          "https://www.deutsche-digitale-bibliothek.de/content/lizenzen/rv-fz"
        ]
      }
    },
    {
      "label": {
        "true": [
          "Description"
        ]
      },
      "value": {
        "true": [
          "Image(s) taken from the Epigraphic Database Heidelberg"
        ]
      }
    }
  ],
  "requiredStatement": {
    "label": {
      "true": [
        true
      ]
    },
    "value": {
      "true": [
        "Heidelberger Akademie der Wissenschaften / Epigraphische Datenbank Heidelberg"
      ]
    }
  },
  "items": [
    {
      "id": "https://edh.ub.uni-heidelberg.de/iiif/edh/canvas/F035406",
      "type": "Canvas",
      "label": {
        "true": [
          "F035406"
        ]
      },
      "metadata": [
        {
          "label": {
            "true": [
              "Foto ID"
            ]
          },
          "value": {
            "true": [
              "https://edh.ub.uni-heidelberg.de/edh/foto/F035406"
            ]
          }
        },
        {
          "label": {
            "true": [
              "Photo credits"
            ]
          },
          "value": {
            "true": [
              "\u00a9 C. Witschel"
            ]
          }
        },
        {
          "label": {
            "true": [
              "Date of photograph"
            ]
          },
          "value": {
            "true": [
              "2012"
            ]
          }
        }
      ],
      "height": 1900,
      "width": 1379,
      "items": [
        {
          "id": "https://example.org/uuid/d141a677-b474-4f16-a44b-2ccedc752492",
          "type": "AnnotationPage",
          "items": [
            {
              "@context": "http://iiif.io/api/presentation/2/context.json",
              "id": "https://edh.ub.uni-heidelberg.de/iiif/edh/annotation/F035406",
              "type": "Annotation",
              "motivation": "painting",
              "target": "https://edh.ub.uni-heidelberg.de/iiif/edh/canvas/f035406",
              "body": {
                "id": "https://edh.ub.uni-heidelberg.de/iiif/edh/resource/F035406",
                "type": "Image",
                "format": "image/png",
                "height": 1900,
                "width": 1379,
                "service": [
                  {
                    "@id": "https://heidicon.ub.uni-heidelberg.de/iiif/2/1447845%3A796255",
                    "@type": "ImageService2",
                    "profile": "http://iiif.io/api/image/2/level2.json"
                  }
                ]
              }
            }
          ]
        }
      ]
    },
    {
      "id": "https://edh.ub.uni-heidelberg.de/iiif/edh/canvas/F035407",
      "type": "Canvas",
      "label": {
        "true": [
          "F035407"
        ]
      },
      "metadata": [
        {
          "label": {
            "true": [
              "Foto ID"
            ]
          },
          "value": {
            "true": [
              "https://edh.ub.uni-heidelberg.de/edh/foto/F035407"
            ]
          }
        },
        {
          "label": {
            "true": [
              "Photo credits"
            ]
          },
          "value": {
            "true": [
              "\u00a9 C. Witschel"
            ]
          }
        },
        {
          "label": {
            "true": [
              "Date of photograph"
            ]
          },
          "value": {
            "true": [
              "2012"
            ]
          }
        }
      ],
      "height": 1850,
      "width": 1445,
      "items": [
        {
          "id": "https://example.org/uuid/5407447c-e099-4d92-b0dd-0e4e1c5cc547",
          "type": "AnnotationPage",
          "items": [
            {
              "@context": "http://iiif.io/api/presentation/2/context.json",
              "id": "https://edh.ub.uni-heidelberg.de/iiif/edh/annotation/F035407",
              "type": "Annotation",
              "motivation": "painting",
              "target": "https://edh.ub.uni-heidelberg.de/iiif/edh/canvas/f035407",
              "body": {
                "id": "https://edh.ub.uni-heidelberg.de/iiif/edh/resource/F035407",
                "type": "Image",
                "format": "image/png",
                "height": 1850,
                "width": 1445,
                "service": [
                  {
                    "@id": "https://heidicon.ub.uni-heidelberg.de/iiif/2/1447846%3A796256",
                    "@type": "ImageService2",
                    "profile": "http://iiif.io/api/image/2/level2.json"
                  }
                ]
              }
            }
          ]
        }
      ]
    }
  ]
}
