{
  "@context": [
    "http://www.w3.org/ns/anno.jsonld",
    "http://iiif.io/api/presentation/3/context.json"
  ],
  "id": "https://ria.ub.uni-heidelberg.de/iiif/ria/HD058499.manifest.json",
  "type": "Manifest",
  "label": {
    "true": [
      "EDH Image HD058499"
    ]
  },
  "metadata": [
    {
      "label": {
        "true": [
          "Provinz / Italische Region"
        ]
      },
      "value": {
        "true": [
          "Raetia"
        ]
      }
    },
    {
      "label": {
        "true": [
          "Land"
        ]
      },
      "value": {
        "true": [
          "Germany"
        ]
      }
    },
    {
      "label": {
        "true": [
          "Fundort antik"
        ]
      },
      "value": {
        "true": [
          "Augusta Vindelicorum"
        ]
      }
    },
    {
      "label": {
        "true": [
          "Fundort modern"
        ]
      },
      "value": {
        "true": [
          "Augsburg"
        ]
      }
    },
    {
      "label": {
        "true": [
          "Aufbewahrung"
        ]
      },
      "value": {
        "true": [
          "Augsburg, R\u00f6m. Mus."
        ]
      }
    },
    {
      "label": {
        "true": [
          true
        ]
      },
      "value": {
        "true": [
          "https://www.deutsche-digitale-bibliothek.de/content/lizenzen/rv-fz"
        ]
      }
    },
    {
      "label": {
        "true": [
          "Description"
        ]
      },
      "value": {
        "true": [
          "Image(s) taken from the Epigraphic Database Heidelberg"
        ]
      }
    }
  ],
  "requiredStatement": {
    "label": {
      "true": [
        true
      ]
    },
    "value": {
      "true": [
        "Heidelberger Akademie der Wissenschaften / Epigraphische Datenbank Heidelberg"
      ]
    }
  },
  "items": [
    {
      "id": "https://edh.ub.uni-heidelberg.de/iiif/edh/canvas/F007358",
      "type": "Canvas",
      "label": {
        "true": [
          "F007358"
        ]
      },
      "metadata": [
        {
          "label": {
            "true": [
              "Foto ID"
            ]
          },
          "value": {
            "true": [
              "https://edh.ub.uni-heidelberg.de/edh/foto/F007358"
            ]
          }
        },
        {
          "label": {
            "true": [
              "Photo credits"
            ]
          },
          "value": {
            "true": [
              "\u00a9 G. Alf\u00f6ldy"
            ]
          }
        },
        {
          "label": {
            "true": [
              "Date of photograph"
            ]
          },
          "value": {
            "true": [
              "1994"
            ]
          }
        }
      ],
      "height": 2000,
      "width": 1378,
      "items": [
        {
          "id": "https://example.org/uuid/7badfda8-3881-4563-8f08-9b918183d3ad",
          "type": "AnnotationPage",
          "items": [
            {
              "@context": "http://iiif.io/api/presentation/2/context.json",
              "id": "https://edh.ub.uni-heidelberg.de/iiif/edh/annotation/F007358",
              "type": "Annotation",
              "motivation": "painting",
              "target": "https://edh.ub.uni-heidelberg.de/iiif/edh/canvas/f007358",
              "body": {
                "id": "https://edh.ub.uni-heidelberg.de/iiif/edh/resource/F007358",
                "type": "Image",
                "format": "image/png",
                "height": 2000,
                "width": 1378,
                "service": [
                  {
                    "@id": "https://heidicon.ub.uni-heidelberg.de/iiif/2/1419426%3A767729",
                    "@type": "ImageService2",
                    "profile": "http://iiif.io/api/image/2/level2.json"
                  }
                ]
              }
            }
          ]
        }
      ]
    },
    {
      "id": "https://edh.ub.uni-heidelberg.de/iiif/edh/canvas/F035481",
      "type": "Canvas",
      "label": {
        "true": [
          "F035481"
        ]
      },
      "metadata": [
        {
          "label": {
            "true": [
              "Foto ID"
            ]
          },
          "value": {
            "true": [
              "https://edh.ub.uni-heidelberg.de/edh/foto/F035481"
            ]
          }
        },
        {
          "label": {
            "true": [
              "Photo credits"
            ]
          },
          "value": {
            "true": [
              "\u00a9 C. Witschel"
            ]
          }
        },
        {
          "label": {
            "true": [
              "Date of photograph"
            ]
          },
          "value": {
            "true": [
              "2012"
            ]
          }
        }
      ],
      "height": 2100,
      "width": 1304,
      "items": [
        {
          "id": "https://example.org/uuid/f0069aaa-90d3-43b5-a146-fa500b380b13",
          "type": "AnnotationPage",
          "items": [
            {
              "@context": "http://iiif.io/api/presentation/2/context.json",
              "id": "https://edh.ub.uni-heidelberg.de/iiif/edh/annotation/F035481",
              "type": "Annotation",
              "motivation": "painting",
              "target": "https://edh.ub.uni-heidelberg.de/iiif/edh/canvas/f035481",
              "body": {
                "id": "https://edh.ub.uni-heidelberg.de/iiif/edh/resource/F035481",
                "type": "Image",
                "format": "image/png",
                "height": 2100,
                "width": 1304,
                "service": [
                  {
                    "@id": "https://heidicon.ub.uni-heidelberg.de/iiif/2/1447920%3A796330",
                    "@type": "ImageService2",
                    "profile": "http://iiif.io/api/image/2/level2.json"
                  }
                ]
              }
            }
          ]
        }
      ]
    },
    {
      "id": "https://edh.ub.uni-heidelberg.de/iiif/edh/canvas/F035482",
      "type": "Canvas",
      "label": {
        "true": [
          "F035482"
        ]
      },
      "metadata": [
        {
          "label": {
            "true": [
              "Foto ID"
            ]
          },
          "value": {
            "true": [
              "https://edh.ub.uni-heidelberg.de/edh/foto/F035482"
            ]
          }
        },
        {
          "label": {
            "true": [
              "Photo credits"
            ]
          },
          "value": {
            "true": [
              "\u00a9 C. Witschel"
            ]
          }
        },
        {
          "label": {
            "true": [
              "Date of photograph"
            ]
          },
          "value": {
            "true": [
              "2012"
            ]
          }
        }
      ],
      "height": 1900,
      "width": 1359,
      "items": [
        {
          "id": "https://example.org/uuid/3bc48ec2-bdfd-4f20-b028-087ef215c51d",
          "type": "AnnotationPage",
          "items": [
            {
              "@context": "http://iiif.io/api/presentation/2/context.json",
              "id": "https://edh.ub.uni-heidelberg.de/iiif/edh/annotation/F035482",
              "type": "Annotation",
              "motivation": "painting",
              "target": "https://edh.ub.uni-heidelberg.de/iiif/edh/canvas/f035482",
              "body": {
                "id": "https://edh.ub.uni-heidelberg.de/iiif/edh/resource/F035482",
                "type": "Image",
                "format": "image/png",
                "height": 1900,
                "width": 1359,
                "service": [
                  {
                    "@id": "https://heidicon.ub.uni-heidelberg.de/iiif/2/1447921%3A796331",
                    "@type": "ImageService2",
                    "profile": "http://iiif.io/api/image/2/level2.json"
                  }
                ]
              }
            }
          ]
        }
      ]
    },
    {
      "id": "https://edh.ub.uni-heidelberg.de/iiif/edh/canvas/F035483",
      "type": "Canvas",
      "label": {
        "true": [
          "F035483"
        ]
      },
      "metadata": [
        {
          "label": {
            "true": [
              "Foto ID"
            ]
          },
          "value": {
            "true": [
              "https://edh.ub.uni-heidelberg.de/edh/foto/F035483"
            ]
          }
        },
        {
          "label": {
            "true": [
              "Photo credits"
            ]
          },
          "value": {
            "true": [
              "\u00a9 C. Witschel"
            ]
          }
        },
        {
          "label": {
            "true": [
              "Date of photograph"
            ]
          },
          "value": {
            "true": [
              "2012"
            ]
          }
        }
      ],
      "height": 2100,
      "width": 1268,
      "items": [
        {
          "id": "https://example.org/uuid/e3ef8da6-ea77-45cb-adb6-75b9d4ec31fa",
          "type": "AnnotationPage",
          "items": [
            {
              "@context": "http://iiif.io/api/presentation/2/context.json",
              "id": "https://edh.ub.uni-heidelberg.de/iiif/edh/annotation/F035483",
              "type": "Annotation",
              "motivation": "painting",
              "target": "https://edh.ub.uni-heidelberg.de/iiif/edh/canvas/f035483",
              "body": {
                "id": "https://edh.ub.uni-heidelberg.de/iiif/edh/resource/F035483",
                "type": "Image",
                "format": "image/png",
                "height": 2100,
                "width": 1268,
                "service": [
                  {
                    "@id": "https://heidicon.ub.uni-heidelberg.de/iiif/2/1447922%3A796332",
                    "@type": "ImageService2",
                    "profile": "http://iiif.io/api/image/2/level2.json"
                  }
                ]
              }
            }
          ]
        }
      ]
    },
    {
      "id": "https://edh.ub.uni-heidelberg.de/iiif/edh/canvas/F035484",
      "type": "Canvas",
      "label": {
        "true": [
          "F035484"
        ]
      },
      "metadata": [
        {
          "label": {
            "true": [
              "Foto ID"
            ]
          },
          "value": {
            "true": [
              "https://edh.ub.uni-heidelberg.de/edh/foto/F035484"
            ]
          }
        },
        {
          "label": {
            "true": [
              "Photo credits"
            ]
          },
          "value": {
            "true": [
              "\u00a9 C. Witschel"
            ]
          }
        },
        {
          "label": {
            "true": [
              "Date of photograph"
            ]
          },
          "value": {
            "true": [
              "2012"
            ]
          }
        }
      ],
      "height": 2000,
      "width": 1297,
      "items": [
        {
          "id": "https://example.org/uuid/44458e30-31b1-4e5b-8e0f-c31e49ce103e",
          "type": "AnnotationPage",
          "items": [
            {
              "@context": "http://iiif.io/api/presentation/2/context.json",
              "id": "https://edh.ub.uni-heidelberg.de/iiif/edh/annotation/F035484",
              "type": "Annotation",
              "motivation": "painting",
              "target": "https://edh.ub.uni-heidelberg.de/iiif/edh/canvas/f035484",
              "body": {
                "id": "https://edh.ub.uni-heidelberg.de/iiif/edh/resource/F035484",
                "type": "Image",
                "format": "image/png",
                "height": 2000,
                "width": 1297,
                "service": [
                  {
                    "@id": "https://heidicon.ub.uni-heidelberg.de/iiif/2/1447923%3A796333",
                    "@type": "ImageService2",
                    "profile": "http://iiif.io/api/image/2/level2.json"
                  }
                ]
              }
            }
          ]
        }
      ]
    },
    {
      "id": "https://edh.ub.uni-heidelberg.de/iiif/edh/canvas/F035485",
      "type": "Canvas",
      "label": {
        "true": [
          "F035485"
        ]
      },
      "metadata": [
        {
          "label": {
            "true": [
              "Foto ID"
            ]
          },
          "value": {
            "true": [
              "https://edh.ub.uni-heidelberg.de/edh/foto/F035485"
            ]
          }
        },
        {
          "label": {
            "true": [
              "Photo credits"
            ]
          },
          "value": {
            "true": [
              "\u00a9 C. Witschel"
            ]
          }
        },
        {
          "label": {
            "true": [
              "Date of photograph"
            ]
          },
          "value": {
            "true": [
              "2012"
            ]
          }
        }
      ],
      "height": 2000,
      "width": 1306,
      "items": [
        {
          "id": "https://example.org/uuid/7d1aaa81-191b-4d10-906e-a67efdda8a14",
          "type": "AnnotationPage",
          "items": [
            {
              "@context": "http://iiif.io/api/presentation/2/context.json",
              "id": "https://edh.ub.uni-heidelberg.de/iiif/edh/annotation/F035485",
              "type": "Annotation",
              "motivation": "painting",
              "target": "https://edh.ub.uni-heidelberg.de/iiif/edh/canvas/f035485",
              "body": {
                "id": "https://edh.ub.uni-heidelberg.de/iiif/edh/resource/F035485",
                "type": "Image",
                "format": "image/png",
                "height": 2000,
                "width": 1306,
                "service": [
                  {
                    "@id": "https://heidicon.ub.uni-heidelberg.de/iiif/2/1447924%3A796334",
                    "@type": "ImageService2",
                    "profile": "http://iiif.io/api/image/2/level2.json"
                  }
                ]
              }
            }
          ]
        }
      ]
    },
    {
      "id": "https://edh.ub.uni-heidelberg.de/iiif/edh/canvas/F036953",
      "type": "Canvas",
      "label": {
        "true": [
          "F036953"
        ]
      },
      "metadata": [
        {
          "label": {
            "true": [
              "Foto ID"
            ]
          },
          "value": {
            "true": [
              "https://edh.ub.uni-heidelberg.de/edh/foto/F036953"
            ]
          }
        },
        {
          "label": {
            "true": [
              "Photo credits"
            ]
          },
          "value": {
            "true": [
              "\u00a9 F. Feraudi-Gru\u00e9nais (Kopie)"
            ]
          }
        },
        {
          "label": {
            "true": [
              "Date of photograph"
            ]
          },
          "value": {
            "true": [
              "2016"
            ]
          }
        }
      ],
      "height": 2000,
      "width": 1217,
      "items": [
        {
          "id": "https://example.org/uuid/65958bb5-6706-42f9-997d-52b140d06bf3",
          "type": "AnnotationPage",
          "items": [
            {
              "@context": "http://iiif.io/api/presentation/2/context.json",
              "id": "https://edh.ub.uni-heidelberg.de/iiif/edh/annotation/F036953",
              "type": "Annotation",
              "motivation": "painting",
              "target": "https://edh.ub.uni-heidelberg.de/iiif/edh/canvas/f036953",
              "body": {
                "id": "https://edh.ub.uni-heidelberg.de/iiif/edh/resource/F036953",
                "type": "Image",
                "format": "image/png",
                "height": 2000,
                "width": 1217,
                "service": [
                  {
                    "@id": "https://heidicon.ub.uni-heidelberg.de/iiif/2/1449403%3A797814",
                    "@type": "ImageService2",
                    "profile": "http://iiif.io/api/image/2/level2.json"
                  }
                ]
              }
            }
          ]
        }
      ]
    },
    {
      "id": "https://edh.ub.uni-heidelberg.de/iiif/edh/canvas/F036954",
      "type": "Canvas",
      "label": {
        "true": [
          "F036954"
        ]
      },
      "metadata": [
        {
          "label": {
            "true": [
              "Foto ID"
            ]
          },
          "value": {
            "true": [
              "https://edh.ub.uni-heidelberg.de/edh/foto/F036954"
            ]
          }
        },
        {
          "label": {
            "true": [
              "Photo credits"
            ]
          },
          "value": {
            "true": [
              "\u00a9 F. Feraudi-Gru\u00e9nais (Kopie)"
            ]
          }
        },
        {
          "label": {
            "true": [
              "Date of photograph"
            ]
          },
          "value": {
            "true": [
              "2016"
            ]
          }
        }
      ],
      "height": 2000,
      "width": 1500,
      "items": [
        {
          "id": "https://example.org/uuid/a1caae33-3c2e-4b51-9f38-b277f29f15ef",
          "type": "AnnotationPage",
          "items": [
            {
              "@context": "http://iiif.io/api/presentation/2/context.json",
              "id": "https://edh.ub.uni-heidelberg.de/iiif/edh/annotation/F036954",
              "type": "Annotation",
              "motivation": "painting",
              "target": "https://edh.ub.uni-heidelberg.de/iiif/edh/canvas/f036954",
              "body": {
                "id": "https://edh.ub.uni-heidelberg.de/iiif/edh/resource/F036954",
                "type": "Image",
                "format": "image/png",
                "height": 2000,
                "width": 1500,
                "service": [
                  {
                    "@id": "https://heidicon.ub.uni-heidelberg.de/iiif/2/1449404%3A797815",
                    "@type": "ImageService2",
                    "profile": "http://iiif.io/api/image/2/level2.json"
                  }
                ]
              }
            }
          ]
        }
      ]
    },
    {
      "id": "https://edh.ub.uni-heidelberg.de/iiif/edh/canvas/F036955",
      "type": "Canvas",
      "label": {
        "true": [
          "F036955"
        ]
      },
      "metadata": [
        {
          "label": {
            "true": [
              "Foto ID"
            ]
          },
          "value": {
            "true": [
              "https://edh.ub.uni-heidelberg.de/edh/foto/F036955"
            ]
          }
        },
        {
          "label": {
            "true": [
              "Photo credits"
            ]
          },
          "value": {
            "true": [
              "\u00a9 F. Feraudi-Gru\u00e9nais (Kopie)"
            ]
          }
        },
        {
          "label": {
            "true": [
              "Date of photograph"
            ]
          },
          "value": {
            "true": [
              "2016"
            ]
          }
        }
      ],
      "height": 2000,
      "width": 1224,
      "items": [
        {
          "id": "https://example.org/uuid/72fa854b-8264-45ff-ba5d-94d9824f384f",
          "type": "AnnotationPage",
          "items": [
            {
              "@context": "http://iiif.io/api/presentation/2/context.json",
              "id": "https://edh.ub.uni-heidelberg.de/iiif/edh/annotation/F036955",
              "type": "Annotation",
              "motivation": "painting",
              "target": "https://edh.ub.uni-heidelberg.de/iiif/edh/canvas/f036955",
              "body": {
                "id": "https://edh.ub.uni-heidelberg.de/iiif/edh/resource/F036955",
                "type": "Image",
                "format": "image/png",
                "height": 2000,
                "width": 1224,
                "service": [
                  {
                    "@id": "https://heidicon.ub.uni-heidelberg.de/iiif/2/1449405%3A797816",
                    "@type": "ImageService2",
                    "profile": "http://iiif.io/api/image/2/level2.json"
                  }
                ]
              }
            }
          ]
        }
      ]
    },
    {
      "id": "https://edh.ub.uni-heidelberg.de/iiif/edh/canvas/F036956",
      "type": "Canvas",
      "label": {
        "true": [
          "F036956"
        ]
      },
      "metadata": [
        {
          "label": {
            "true": [
              "Foto ID"
            ]
          },
          "value": {
            "true": [
              "https://edh.ub.uni-heidelberg.de/edh/foto/F036956"
            ]
          }
        },
        {
          "label": {
            "true": [
              "Photo credits"
            ]
          },
          "value": {
            "true": [
              "\u00a9 F. Feraudi-Gru\u00e9nais (Kopie)"
            ]
          }
        },
        {
          "label": {
            "true": [
              "Date of photograph"
            ]
          },
          "value": {
            "true": [
              "2016"
            ]
          }
        }
      ],
      "height": 2000,
      "width": 1500,
      "items": [
        {
          "id": "https://example.org/uuid/7f2b2ee6-6b70-4722-9ebc-870bdccb89fc",
          "type": "AnnotationPage",
          "items": [
            {
              "@context": "http://iiif.io/api/presentation/2/context.json",
              "id": "https://edh.ub.uni-heidelberg.de/iiif/edh/annotation/F036956",
              "type": "Annotation",
              "motivation": "painting",
              "target": "https://edh.ub.uni-heidelberg.de/iiif/edh/canvas/f036956",
              "body": {
                "id": "https://edh.ub.uni-heidelberg.de/iiif/edh/resource/F036956",
                "type": "Image",
                "format": "image/png",
                "height": 2000,
                "width": 1500,
                "service": [
                  {
                    "@id": "https://heidicon.ub.uni-heidelberg.de/iiif/2/1449406%3A797817",
                    "@type": "ImageService2",
                    "profile": "http://iiif.io/api/image/2/level2.json"
                  }
                ]
              }
            }
          ]
        }
      ]
    },
    {
      "id": "https://ria.ub.uni-heidelberg.de/iiif/ria/canvas/Pv3r9JPASJSjqXeqF1rodw",
      "type": "Canvas",
      "label": {
        "true": [
          "Mezger: R\u00f6mische Steindenkm\u00e4ler (1862): 42"
        ]
      },
      "height": "1232.6550000000002",
      "width": "1038.3175000000006",
      "metadata": [
        {
          "label": {
            "true": [
              "EDH"
            ]
          },
          "value": {
            "true": [
              "HD058499"
            ]
          }
        },
        {
          "label": {
            "true": [
              "Source Link"
            ]
          },
          "value": {
            "true": [
              "https://digi.ub.uni-heidelberg.de/diglit/mezger1862/0042"
            ]
          }
        },
        {
          "label": {
            "true": [
              "Photo Credit"
            ]
          },
          "value": {
            "true": [
              "UB Heidelberg"
            ]
          }
        },
        {
          "label": {
            "true": [
              "Aufbewahrung"
            ]
          },
          "value": {
            "true": [
              "UB Heidelberg"
            ]
          }
        }
      ],
      "items": [
        {
          "id": "https:/ria.ub.uni-heidelberg.de/uuid/Pv3r9JPASJSjqXeqF1rodw",
          "type": "AnnotationPage",
          "items": [
            {
              "@context": "http://iiif.io/api/presentation/2/context.json",
              "id": "https://edh.ub.uni-heidelberg.de/iiif/edh/annotation/Pv3r9JPASJSjqXeqF1rodw",
              "type": "Annotation",
              "motivation": "painting",
              "target": "https://ria.ub.uni-heidelberg.de/iiif/ria/canvas/Pv3r9JPASJSjqXeqF1rodw",
              "body": {
                "id": "https://digi.ub.uni-heidelberg.de/iiif/2/mezger1862%3A24.jpg/219.64250000000004,716.2725,1038.3175000000006,1232.6550000000002/full/0/default.jpg",
                "type": "Image",
                "format": "image/png",
                "height": "1232.6550000000002",
                "width": "1038.3175000000006"
              }
            }
          ]
        }
      ]
    },
    {
      "id": "https://ria.ub.uni-heidelberg.de/iiif/ria/canvas/WU_bHmsgTKqsoGr6M8j_Wg",
      "type": "Canvas",
      "label": {
        "true": [
          "Raiser: R\u00f6mische Alterth\u00fcmer (1820): 37"
        ]
      },
      "height": "268.01100501699307",
      "width": "698.2391972811134",
      "metadata": [
        {
          "label": {
            "true": [
              "EDH"
            ]
          },
          "value": {
            "true": [
              "HD058499"
            ]
          }
        },
        {
          "label": {
            "true": [
              "Source Link"
            ]
          },
          "value": {
            "true": [
              "https://digi.ub.uni-heidelberg.de/diglit/raiser1820/0037"
            ]
          }
        },
        {
          "label": {
            "true": [
              "Photo Credit"
            ]
          },
          "value": {
            "true": [
              "UB Heidelberg"
            ]
          }
        },
        {
          "label": {
            "true": [
              "Aufbewahrung"
            ]
          },
          "value": {
            "true": [
              "UB Heidelberg"
            ]
          }
        }
      ],
      "items": [
        {
          "id": "https:/ria.ub.uni-heidelberg.de/uuid/WU_bHmsgTKqsoGr6M8j_Wg",
          "type": "AnnotationPage",
          "items": [
            {
              "@context": "http://iiif.io/api/presentation/2/context.json",
              "id": "https://edh.ub.uni-heidelberg.de/iiif/edh/annotation/WU_bHmsgTKqsoGr6M8j_Wg",
              "type": "Annotation",
              "motivation": "painting",
              "target": "https://ria.ub.uni-heidelberg.de/iiif/ria/canvas/WU_bHmsgTKqsoGr6M8j_Wg",
              "body": {
                "id": "https://digi.ub.uni-heidelberg.de/iiif/2/raiser1820%3A027.jpg/850.5529211846575,1523.2546528564492,698.2391972811134,268.01100501699307/full/0/default.jpg",
                "type": "Image",
                "format": "image/png",
                "height": "268.01100501699307",
                "width": "698.2391972811134"
              }
            }
          ]
        }
      ]
    },
    {
      "id": "https://ria.ub.uni-heidelberg.de/iiif/ria/canvas/Tu5AXMl2Sb2tUrbmJbIl6w",
      "type": "Canvas",
      "label": {
        "true": [
          "Raiser: R\u00f6mische Alterth\u00fcmer (1820): 38"
        ]
      },
      "height": "375.87750000000005",
      "width": "708.1750000000001",
      "metadata": [
        {
          "label": {
            "true": [
              "EDH"
            ]
          },
          "value": {
            "true": [
              "HD058499"
            ]
          }
        },
        {
          "label": {
            "true": [
              "Source Link"
            ]
          },
          "value": {
            "true": [
              "https://digi.ub.uni-heidelberg.de/diglit/raiser1820/0038"
            ]
          }
        },
        {
          "label": {
            "true": [
              "Photo Credit"
            ]
          },
          "value": {
            "true": [
              "UB Heidelberg"
            ]
          }
        },
        {
          "label": {
            "true": [
              "Aufbewahrung"
            ]
          },
          "value": {
            "true": [
              "UB Heidelberg"
            ]
          }
        }
      ],
      "items": [
        {
          "id": "https:/ria.ub.uni-heidelberg.de/uuid/Tu5AXMl2Sb2tUrbmJbIl6w",
          "type": "AnnotationPage",
          "items": [
            {
              "@context": "http://iiif.io/api/presentation/2/context.json",
              "id": "https://edh.ub.uni-heidelberg.de/iiif/edh/annotation/Tu5AXMl2Sb2tUrbmJbIl6w",
              "type": "Annotation",
              "motivation": "painting",
              "target": "https://ria.ub.uni-heidelberg.de/iiif/ria/canvas/Tu5AXMl2Sb2tUrbmJbIl6w",
              "body": {
                "id": "https://digi.ub.uni-heidelberg.de/iiif/2/raiser1820%3A028.jpg/135.32499999999993,234.24249999999998,708.1750000000001,375.87750000000005/full/0/default.jpg",
                "type": "Image",
                "format": "image/png",
                "height": "375.87750000000005",
                "width": "708.1750000000001"
              }
            }
          ]
        }
      ]
    },
    {
      "id": "https://ria.ub.uni-heidelberg.de/iiif/ria/canvas/RYlOKIHfRBytrkJNMk-MJw",
      "type": "Canvas",
      "label": {
        "true": [
          "Raiser: R\u00f6mische Alterth\u00fcmer (1820): 39"
        ]
      },
      "height": "1525.3",
      "width": "702.7274999999998",
      "metadata": [
        {
          "label": {
            "true": [
              "EDH"
            ]
          },
          "value": {
            "true": [
              "HD058499"
            ]
          }
        },
        {
          "label": {
            "true": [
              "Source Link"
            ]
          },
          "value": {
            "true": [
              "https://digi.ub.uni-heidelberg.de/diglit/raiser1820/0039"
            ]
          }
        },
        {
          "label": {
            "true": [
              "Photo Credit"
            ]
          },
          "value": {
            "true": [
              "UB Heidelberg"
            ]
          }
        },
        {
          "label": {
            "true": [
              "Aufbewahrung"
            ]
          },
          "value": {
            "true": [
              "UB Heidelberg"
            ]
          }
        }
      ],
      "items": [
        {
          "id": "https:/ria.ub.uni-heidelberg.de/uuid/RYlOKIHfRBytrkJNMk-MJw",
          "type": "AnnotationPage",
          "items": [
            {
              "@context": "http://iiif.io/api/presentation/2/context.json",
              "id": "https://edh.ub.uni-heidelberg.de/iiif/edh/annotation/RYlOKIHfRBytrkJNMk-MJw",
              "type": "Annotation",
              "motivation": "painting",
              "target": "https://ria.ub.uni-heidelberg.de/iiif/ria/canvas/RYlOKIHfRBytrkJNMk-MJw",
              "body": {
                "id": "https://digi.ub.uni-heidelberg.de/iiif/2/raiser1820%3A029.jpg/108.08749999999998,228.795,702.7274999999998,1525.3/full/0/default.jpg",
                "type": "Image",
                "format": "image/png",
                "height": "1525.3",
                "width": "702.7274999999998"
              }
            }
          ]
        }
      ]
    },
    {
      "id": "https://ria.ub.uni-heidelberg.de/iiif/ria/canvas/EOsqt3G6T_mosgrLNUbqQw",
      "type": "Canvas",
      "label": {
        "true": [
          "Vollmer: Inscriptiones Baivariae Romanae (1915): 50"
        ]
      },
      "height": "1736.9850000000004",
      "width": "794.4350000000002",
      "metadata": [
        {
          "label": {
            "true": [
              "EDH"
            ]
          },
          "value": {
            "true": [
              "HD058499"
            ]
          }
        },
        {
          "label": {
            "true": [
              "Source Link"
            ]
          },
          "value": {
            "true": [
              "https://digi.ub.uni-heidelberg.de/diglit/vollmer1915/0050"
            ]
          }
        },
        {
          "label": {
            "true": [
              "Photo Credit"
            ]
          },
          "value": {
            "true": [
              "UB Heidelberg"
            ]
          }
        },
        {
          "label": {
            "true": [
              "Aufbewahrung"
            ]
          },
          "value": {
            "true": [
              "UB Heidelberg"
            ]
          }
        }
      ],
      "items": [
        {
          "id": "https:/ria.ub.uni-heidelberg.de/uuid/EOsqt3G6T_mosgrLNUbqQw",
          "type": "AnnotationPage",
          "items": [
            {
              "@context": "http://iiif.io/api/presentation/2/context.json",
              "id": "https://edh.ub.uni-heidelberg.de/iiif/edh/annotation/EOsqt3G6T_mosgrLNUbqQw",
              "type": "Annotation",
              "motivation": "painting",
              "target": "https://ria.ub.uni-heidelberg.de/iiif/ria/canvas/EOsqt3G6T_mosgrLNUbqQw",
              "body": {
                "id": "https://digi.ub.uni-heidelberg.de/iiif/2/vollmer1915%3A0000_038.jpg/1024.3719104829045,268.44433566089515,794.4350000000002,1736.9850000000004/full/0/default.jpg",
                "type": "Image",
                "format": "image/png",
                "height": "1736.9850000000004",
                "width": "794.4350000000002"
              }
            }
          ]
        }
      ]
    },
    {
      "id": "https://ria.ub.uni-heidelberg.de/iiif/ria/canvas/TpnZ7BpjSFWjgvjFj3-7XQ",
      "type": "Canvas",
      "label": {
        "true": [
          "Vollmer: Inscriptiones Baivariae Romanae (1915): 291"
        ]
      },
      "height": "734.8551959114141",
      "width": "459.28449744463364",
      "metadata": [
        {
          "label": {
            "true": [
              "EDH"
            ]
          },
          "value": {
            "true": [
              "HD058499"
            ]
          }
        },
        {
          "label": {
            "true": [
              "Source Link"
            ]
          },
          "value": {
            "true": [
              "https://digi.ub.uni-heidelberg.de/diglit/vollmer1915/0291"
            ]
          }
        },
        {
          "label": {
            "true": [
              "Photo Credit"
            ]
          },
          "value": {
            "true": [
              "UB Heidelberg"
            ]
          }
        },
        {
          "label": {
            "true": [
              "Aufbewahrung"
            ]
          },
          "value": {
            "true": [
              "UB Heidelberg"
            ]
          }
        }
      ],
      "items": [
        {
          "id": "https:/ria.ub.uni-heidelberg.de/uuid/TpnZ7BpjSFWjgvjFj3-7XQ",
          "type": "AnnotationPage",
          "items": [
            {
              "@context": "http://iiif.io/api/presentation/2/context.json",
              "id": "https://edh.ub.uni-heidelberg.de/iiif/edh/annotation/TpnZ7BpjSFWjgvjFj3-7XQ",
              "type": "Annotation",
              "motivation": "painting",
              "target": "https://ria.ub.uni-heidelberg.de/iiif/ria/canvas/TpnZ7BpjSFWjgvjFj3-7XQ",
              "body": {
                "id": "https://digi.ub.uni-heidelberg.de/iiif/2/vollmer1915%3A00_Tabula_16.jpg/1151.217427675719,678.1147668686797,459.28449744463364,734.8551959114141/full/0/default.jpg",
                "type": "Image",
                "format": "image/png",
                "height": "734.8551959114141",
                "width": "459.28449744463364"
              }
            }
          ]
        }
      ]
    },
    {
      "id": "https://ria.ub.uni-heidelberg.de/iiif/ria/canvas/DcJBBNDATh2-K2E5xAC7vA",
      "type": "Canvas",
      "label": {
        "true": [
          "Hefner: R\u00f6misches Bayern (1852): 99"
        ]
      },
      "height": "1214.58",
      "width": "969.7050000000002",
      "metadata": [
        {
          "label": {
            "true": [
              "EDH"
            ]
          },
          "value": {
            "true": [
              "HD058499"
            ]
          }
        },
        {
          "label": {
            "true": [
              "Source Link"
            ]
          },
          "value": {
            "true": [
              "https://digi.ub.uni-heidelberg.de/diglit/hefner1852text/0099"
            ]
          }
        },
        {
          "label": {
            "true": [
              "Photo Credit"
            ]
          },
          "value": {
            "true": [
              "UB Heidelberg"
            ]
          }
        },
        {
          "label": {
            "true": [
              "Aufbewahrung"
            ]
          },
          "value": {
            "true": [
              "UB Heidelberg"
            ]
          }
        }
      ],
      "items": [
        {
          "id": "https:/ria.ub.uni-heidelberg.de/uuid/DcJBBNDATh2-K2E5xAC7vA",
          "type": "AnnotationPage",
          "items": [
            {
              "@context": "http://iiif.io/api/presentation/2/context.json",
              "id": "https://edh.ub.uni-heidelberg.de/iiif/edh/annotation/DcJBBNDATh2-K2E5xAC7vA",
              "type": "Annotation",
              "motivation": "painting",
              "target": "https://ria.ub.uni-heidelberg.de/iiif/ria/canvas/DcJBBNDATh2-K2E5xAC7vA",
              "body": {
                "id": "https://digi.ub.uni-heidelberg.de/iiif/2/hefner1852text%3A083.jpg/18.569999999999823,524.0325,969.7050000000002,1214.58/full/0/default.jpg",
                "type": "Image",
                "format": "image/png",
                "height": "1214.58",
                "width": "969.7050000000002"
              }
            }
          ]
        }
      ]
    },
    {
      "id": "https://ria.ub.uni-heidelberg.de/iiif/ria/canvas/ZmvASGsHSPuK78JzuzMZTQ",
      "type": "Canvas",
      "label": {
        "true": [
          "Hefner: R\u00f6misches Bayern (1852): 100"
        ]
      },
      "height": "322.17150528612177",
      "width": "1002.6766235945629",
      "metadata": [
        {
          "label": {
            "true": [
              "EDH"
            ]
          },
          "value": {
            "true": [
              "HD058499"
            ]
          }
        },
        {
          "label": {
            "true": [
              "Source Link"
            ]
          },
          "value": {
            "true": [
              "https://digi.ub.uni-heidelberg.de/diglit/hefner1852text/0100"
            ]
          }
        },
        {
          "label": {
            "true": [
              "Photo Credit"
            ]
          },
          "value": {
            "true": [
              "UB Heidelberg"
            ]
          }
        },
        {
          "label": {
            "true": [
              "Aufbewahrung"
            ]
          },
          "value": {
            "true": [
              "UB Heidelberg"
            ]
          }
        }
      ],
      "items": [
        {
          "id": "https:/ria.ub.uni-heidelberg.de/uuid/ZmvASGsHSPuK78JzuzMZTQ",
          "type": "AnnotationPage",
          "items": [
            {
              "@context": "http://iiif.io/api/presentation/2/context.json",
              "id": "https://edh.ub.uni-heidelberg.de/iiif/edh/annotation/ZmvASGsHSPuK78JzuzMZTQ",
              "type": "Annotation",
              "motivation": "painting",
              "target": "https://ria.ub.uni-heidelberg.de/iiif/ria/canvas/ZmvASGsHSPuK78JzuzMZTQ",
              "body": {
                "id": "https://digi.ub.uni-heidelberg.de/iiif/2/hefner1852text%3A084.jpg/71.60513508978016,105.03448565195515,1002.6766235945629,322.17150528612177/full/0/default.jpg",
                "type": "Image",
                "format": "image/png",
                "height": "322.17150528612177",
                "width": "1002.6766235945629"
              }
            }
          ]
        }
      ]
    },
    {
      "id": "https://ria.ub.uni-heidelberg.de/iiif/ria/canvas/G5_DbiJDQqapdUmHvaXyHA",
      "type": "Canvas",
      "label": {
        "true": [
          "Mommsen: Corpus Inscriptionum Latinarum III.2 (1873): 136"
        ]
      },
      "height": "1046.3348416289598",
      "width": "1394.0497737556568",
      "metadata": [
        {
          "label": {
            "true": [
              "EDH"
            ]
          },
          "value": {
            "true": [
              "HD058499"
            ]
          }
        },
        {
          "label": {
            "true": [
              "Source Link"
            ]
          },
          "value": {
            "true": [
              "https://digi.ub.uni-heidelberg.de/diglit/cil_3_2/0136"
            ]
          }
        },
        {
          "label": {
            "true": [
              "Photo Credit"
            ]
          },
          "value": {
            "true": [
              "UB Heidelberg"
            ]
          }
        },
        {
          "label": {
            "true": [
              "Aufbewahrung"
            ]
          },
          "value": {
            "true": [
              "UB Heidelberg"
            ]
          }
        }
      ],
      "items": [
        {
          "id": "https:/ria.ub.uni-heidelberg.de/uuid/G5_DbiJDQqapdUmHvaXyHA",
          "type": "AnnotationPage",
          "items": [
            {
              "@context": "http://iiif.io/api/presentation/2/context.json",
              "id": "https://edh.ub.uni-heidelberg.de/iiif/edh/annotation/G5_DbiJDQqapdUmHvaXyHA",
              "type": "Annotation",
              "motivation": "painting",
              "target": "https://ria.ub.uni-heidelberg.de/iiif/ria/canvas/G5_DbiJDQqapdUmHvaXyHA",
              "body": {
                "id": "https://digi.ub.uni-heidelberg.de/iiif/2/cil_3_2%3A0_0714.jpg/131.35181892885095,1623.0202079097546,1394.0497737556568,1046.3348416289598/full/0/default.jpg",
                "type": "Image",
                "format": "image/png",
                "height": "1046.3348416289598",
                "width": "1394.0497737556568"
              }
            }
          ]
        }
      ]
    },
    {
      "id": "https://ria.ub.uni-heidelberg.de/iiif/ria/canvas/807c18ee-6592-48b5-b421-72ed15922247",
      "type": "Canvas",
      "label": {
        "true": [
          "Schelhorn: Amoenitates literariae V (1726)"
        ]
      },
      "height": "1688",
      "width": "983",
      "metadata": [
        {
          "label": {
            "true": [
              "EDH"
            ]
          },
          "value": {
            "true": [
              "HD058499"
            ]
          }
        },
        {
          "label": {
            "true": [
              "Photo Credit"
            ]
          },
          "value": {
            "true": [
              "M\u00fcnchener Digitalisierungszentrum"
            ]
          }
        },
        {
          "label": {
            "true": [
              "Aufbewahrung"
            ]
          },
          "value": {
            "true": [
              "M\u00fcnchen, Bayerische Staatsbibliothek -- Var. 96 m-5"
            ]
          }
        },
        {
          "label": {
            "true": [
              "Source Link"
            ]
          },
          "value": {
            "true": [
              "https://www.digitale-sammlungen.de/de/view/bsb10135429?page=00139"
            ]
          }
        },
        {
          "label": {
            "true": [
              "BSB-Nummer"
            ]
          },
          "value": {
            "true": [
              "BSB-ID 12101332"
            ]
          }
        }
      ],
      "items": [
        {
          "id": "https:/ria.ub.uni-heidelberg.de/uuid/807c18ee-6592-48b5-b421-72ed15922247",
          "type": "AnnotationPage",
          "items": [
            {
              "@context": "http://iiif.io/api/presentation/2/context.json",
              "id": "https://edh.ub.uni-heidelberg.de/iiif/edh/annotation/807c18ee-6592-48b5-b421-72ed15922247",
              "type": "Annotation",
              "motivation": "painting",
              "target": "https://ria.ub.uni-heidelberg.de/iiif/ria/canvas/807c18ee-6592-48b5-b421-72ed15922247",
              "body": {
                "id": "https://api.digitale-sammlungen.de/iiif/image/v2/bsb10135429_00139/44,169,983,1688/full/0/default.jpg",
                "type": "Image",
                "format": "image/png",
                "height": "1688",
                "width": "983"
              }
            }
          ]
        }
      ]
    },
    {
      "id": "https://ria.ub.uni-heidelberg.de/iiif/ria/canvas/9455634b-b02f-4923-981f-918249233877",
      "type": "Canvas",
      "label": {
        "true": [
          "Raiser: Ober-Donau-Kreis III (1832)"
        ]
      },
      "height": "1211",
      "width": "889",
      "metadata": [
        {
          "label": {
            "true": [
              "EDH"
            ]
          },
          "value": {
            "true": [
              "HD058499"
            ]
          }
        },
        {
          "label": {
            "true": [
              "Photo Credit"
            ]
          },
          "value": {
            "true": [
              "M\u00fcnchener Digitalisierungszentrum"
            ]
          }
        },
        {
          "label": {
            "true": [
              "Aufbewahrung"
            ]
          },
          "value": {
            "true": [
              "Bamberg, Staatsbiblitohek -- HV.H.Bav.654#3"
            ]
          }
        },
        {
          "label": {
            "true": [
              "Source Link"
            ]
          },
          "value": {
            "true": [
              "https://www.digitale-sammlungen.de/de/view/bsb11692243?page=00077"
            ]
          }
        },
        {
          "label": {
            "true": [
              "BSB-Nummer"
            ]
          },
          "value": {
            "true": [
              "BSB-ID 2016252"
            ]
          }
        }
      ],
      "items": [
        {
          "id": "https:/ria.ub.uni-heidelberg.de/uuid/9455634b-b02f-4923-981f-918249233877",
          "type": "AnnotationPage",
          "items": [
            {
              "@context": "http://iiif.io/api/presentation/2/context.json",
              "id": "https://edh.ub.uni-heidelberg.de/iiif/edh/annotation/9455634b-b02f-4923-981f-918249233877",
              "type": "Annotation",
              "motivation": "painting",
              "target": "https://ria.ub.uni-heidelberg.de/iiif/ria/canvas/9455634b-b02f-4923-981f-918249233877",
              "body": {
                "id": "https://api.digitale-sammlungen.de/iiif/image/v2/bsb11692243_00077/1064,641,889,1211/full/0/default.jpg ",
                "type": "Image",
                "format": "image/png",
                "height": "1211",
                "width": "889"
              }
            }
          ]
        }
      ]
    },
    {
      "id": "https://ria.ub.uni-heidelberg.de/iiif/ria/canvas/4c6bd946-7acf-477e-8c54-fc01051d61c9",
      "type": "Canvas",
      "label": {
        "true": [
          "Pococke: Inscriptionum antiquarum (1752)"
        ]
      },
      "height": "650",
      "width": "734",
      "metadata": [
        {
          "label": {
            "true": [
              "EDH"
            ]
          },
          "value": {
            "true": [
              "HD058499"
            ]
          }
        },
        {
          "label": {
            "true": [
              "Photo Credit"
            ]
          },
          "value": {
            "true": [
              "M\u00fcnchener Digitalisierungszentrum"
            ]
          }
        },
        {
          "label": {
            "true": [
              "Aufbewahrung"
            ]
          },
          "value": {
            "true": [
              "M\u00fcnchen, Bayerische Staatsbibliothek -- 2 Arch. 214"
            ]
          }
        },
        {
          "label": {
            "true": [
              "Source Link"
            ]
          },
          "value": {
            "true": [
              "https://www.digitale-sammlungen.de/de/view/bsb10211868?page=00133"
            ]
          }
        },
        {
          "label": {
            "true": [
              "BSB-Nummer"
            ]
          },
          "value": {
            "true": [
              "BSB-ID 1074358"
            ]
          }
        }
      ],
      "items": [
        {
          "id": "https:/ria.ub.uni-heidelberg.de/uuid/4c6bd946-7acf-477e-8c54-fc01051d61c9",
          "type": "AnnotationPage",
          "items": [
            {
              "@context": "http://iiif.io/api/presentation/2/context.json",
              "id": "https://edh.ub.uni-heidelberg.de/iiif/edh/annotation/4c6bd946-7acf-477e-8c54-fc01051d61c9",
              "type": "Annotation",
              "motivation": "painting",
              "target": "https://ria.ub.uni-heidelberg.de/iiif/ria/canvas/4c6bd946-7acf-477e-8c54-fc01051d61c9",
              "body": {
                "id": "https://api.digitale-sammlungen.de/iiif/image/v2/bsb10211868_00133/654,1466,734,650/full/0/default.jpg ",
                "type": "Image",
                "format": "image/png",
                "height": "650",
                "width": "734"
              }
            }
          ]
        }
      ]
    },
    {
      "id": "https://ria.ub.uni-heidelberg.de/iiif/ria/canvas/f246551b-7ef4-436a-8784-e16bc592696c",
      "type": "Canvas",
      "label": {
        "true": [
          "Orelli: Inscriptionum Latinarum collectio II (1828) - 1. Teil"
        ]
      },
      "height": "269",
      "width": "1284",
      "metadata": [
        {
          "label": {
            "true": [
              "EDH"
            ]
          },
          "value": {
            "true": [
              "HD058499"
            ]
          }
        },
        {
          "label": {
            "true": [
              "Photo Credit"
            ]
          },
          "value": {
            "true": [
              "M\u00fcnchener Digitalisierungszentrum"
            ]
          }
        },
        {
          "label": {
            "true": [
              "Aufbewahrung"
            ]
          },
          "value": {
            "true": [
              "M\u00fcnchen, Bayerische staatsbibliothek -- Arch. 111 m-2"
            ]
          }
        },
        {
          "label": {
            "true": [
              "Source Link"
            ]
          },
          "value": {
            "true": [
              "https://www.digitale-sammlungen.de/de/view/bsb10257262?page=00292"
            ]
          }
        },
        {
          "label": {
            "true": [
              "BSB-Nummer"
            ]
          },
          "value": {
            "true": [
              "BSB-ID 7338229"
            ]
          }
        }
      ],
      "items": [
        {
          "id": "https:/ria.ub.uni-heidelberg.de/uuid/f246551b-7ef4-436a-8784-e16bc592696c",
          "type": "AnnotationPage",
          "items": [
            {
              "@context": "http://iiif.io/api/presentation/2/context.json",
              "id": "https://edh.ub.uni-heidelberg.de/iiif/edh/annotation/f246551b-7ef4-436a-8784-e16bc592696c",
              "type": "Annotation",
              "motivation": "painting",
              "target": "https://ria.ub.uni-heidelberg.de/iiif/ria/canvas/f246551b-7ef4-436a-8784-e16bc592696c",
              "body": {
                "id": "https://api.digitale-sammlungen.de/iiif/image/v2/bsb10257262_00292/209,2153,1284,269/full/0/default.jpg ",
                "type": "Image",
                "format": "image/png",
                "height": "269",
                "width": "1284"
              }
            }
          ]
        }
      ]
    },
    {
      "id": "https://ria.ub.uni-heidelberg.de/iiif/ria/canvas/573e2810-6057-45b0-b29b-deb528c454a7",
      "type": "Canvas",
      "label": {
        "true": [
          "Orelli: Inscriptionum Latinarum collectio II (1828) - 2. Teil"
        ]
      },
      "height": "303",
      "width": "1360",
      "metadata": [
        {
          "label": {
            "true": [
              "EDH"
            ]
          },
          "value": {
            "true": [
              "HD058499"
            ]
          }
        },
        {
          "label": {
            "true": [
              "Photo Credit"
            ]
          },
          "value": {
            "true": [
              "M\u00fcnchener Digitalisierungszentrum"
            ]
          }
        },
        {
          "label": {
            "true": [
              "Aufbewahrung"
            ]
          },
          "value": {
            "true": [
              "M\u00fcnchen, Bayerische staatsbibliothek -- Arch. 111 m-2"
            ]
          }
        },
        {
          "label": {
            "true": [
              "Source Link"
            ]
          },
          "value": {
            "true": [
              "https://www.digitale-sammlungen.de/de/view/bsb10257262?page=00293"
            ]
          }
        },
        {
          "label": {
            "true": [
              "BSB-Nummer"
            ]
          },
          "value": {
            "true": [
              "BSB-ID 7338229"
            ]
          }
        }
      ],
      "items": [
        {
          "id": "https:/ria.ub.uni-heidelberg.de/uuid/573e2810-6057-45b0-b29b-deb528c454a7",
          "type": "AnnotationPage",
          "items": [
            {
              "@context": "http://iiif.io/api/presentation/2/context.json",
              "id": "https://edh.ub.uni-heidelberg.de/iiif/edh/annotation/573e2810-6057-45b0-b29b-deb528c454a7",
              "type": "Annotation",
              "motivation": "painting",
              "target": "https://ria.ub.uni-heidelberg.de/iiif/ria/canvas/573e2810-6057-45b0-b29b-deb528c454a7",
              "body": {
                "id": "https://api.digitale-sammlungen.de/iiif/image/v2/bsb10257262_00293/194,238,1360,303/full/0/default.jpg ",
                "type": "Image",
                "format": "image/png",
                "height": "303",
                "width": "1360"
              }
            }
          ]
        }
      ]
    },
    {
      "id": "https://ria.ub.uni-heidelberg.de/iiif/ria/canvas/0279e7aa-99cd-49a1-b4fd-7c3f0f8107aa",
      "type": "Canvas",
      "label": {
        "true": [
          "CIL - Corpus inscriptionum Latinarum III (1873)"
        ]
      },
      "height": "1283",
      "width": "1740",
      "metadata": [
        {
          "label": {
            "true": [
              "EDH"
            ]
          },
          "value": {
            "true": [
              "HD058499"
            ]
          }
        },
        {
          "label": {
            "true": [
              "Photo Credit"
            ]
          },
          "value": {
            "true": [
              "M\u00fcnchener Digitalisierungszentrum"
            ]
          }
        },
        {
          "label": {
            "true": [
              "Aufbewahrung"
            ]
          },
          "value": {
            "true": [
              "M\u00fcnchen, Bayerische Staatsbibliothek -- 4 Arch. 36 u-3,2"
            ]
          }
        },
        {
          "label": {
            "true": [
              "Source Link"
            ]
          },
          "value": {
            "true": [
              "https://www.digitale-sammlungen.de/de/view/bsb11135214?page=00140"
            ]
          }
        },
        {
          "label": {
            "true": [
              "BSB-Nummer"
            ]
          },
          "value": {
            "true": [
              "BSB-ID 12685798"
            ]
          }
        }
      ],
      "items": [
        {
          "id": "https:/ria.ub.uni-heidelberg.de/uuid/0279e7aa-99cd-49a1-b4fd-7c3f0f8107aa",
          "type": "AnnotationPage",
          "items": [
            {
              "@context": "http://iiif.io/api/presentation/2/context.json",
              "id": "https://edh.ub.uni-heidelberg.de/iiif/edh/annotation/0279e7aa-99cd-49a1-b4fd-7c3f0f8107aa",
              "type": "Annotation",
              "motivation": "painting",
              "target": "https://ria.ub.uni-heidelberg.de/iiif/ria/canvas/0279e7aa-99cd-49a1-b4fd-7c3f0f8107aa",
              "body": {
                "id": "https://api.digitale-sammlungen.de/iiif/image/v2/bsb11135214_00140/370,2138,1740,1283/full/0/default.jpg ",
                "type": "Image",
                "format": "image/png",
                "height": "1283",
                "width": "1740"
              }
            }
          ]
        }
      ]
    },
    {
      "id": "https://ria.ub.uni-heidelberg.de/iiif/ria/canvas/26d55fc7-e40c-46b1-9d19-ba56c355bfef",
      "type": "Canvas",
      "label": {
        "true": [
          "Beck: Monumenta Antiqua Judaica, Augustae Vindel. (1686)"
        ]
      },
      "height": "790",
      "width": "606",
      "metadata": [
        {
          "label": {
            "true": [
              "EDH"
            ]
          },
          "value": {
            "true": [
              "HD058499"
            ]
          }
        },
        {
          "label": {
            "true": [
              "Photo Credit"
            ]
          },
          "value": {
            "true": [
              "M\u00fcnchener Digitalisierungszentrum"
            ]
          }
        },
        {
          "label": {
            "true": [
              "Aufbewahrung"
            ]
          },
          "value": {
            "true": [
              "M\u00fcnchen, Bayerische Staatsbibliothekt -- Jud. 6"
            ]
          }
        },
        {
          "label": {
            "true": [
              "Source Link"
            ]
          },
          "value": {
            "true": [
              "https://www.digitale-sammlungen.de/de/view/bsb10570254?page=00047"
            ]
          }
        },
        {
          "label": {
            "true": [
              "BSB-Nummer"
            ]
          },
          "value": {
            "true": [
              "BSB-ID 2634552"
            ]
          }
        }
      ],
      "items": [
        {
          "id": "https:/ria.ub.uni-heidelberg.de/uuid/26d55fc7-e40c-46b1-9d19-ba56c355bfef",
          "type": "AnnotationPage",
          "items": [
            {
              "@context": "http://iiif.io/api/presentation/2/context.json",
              "id": "https://edh.ub.uni-heidelberg.de/iiif/edh/annotation/26d55fc7-e40c-46b1-9d19-ba56c355bfef",
              "type": "Annotation",
              "motivation": "painting",
              "target": "https://ria.ub.uni-heidelberg.de/iiif/ria/canvas/26d55fc7-e40c-46b1-9d19-ba56c355bfef",
              "body": {
                "id": "https://api.digitale-sammlungen.de/iiif/image/v2/bsb10570254_00047/187,308,606,790/full/0/default.jpg ",
                "type": "Image",
                "format": "image/png",
                "height": "790",
                "width": "606"
              }
            }
          ]
        }
      ]
    }
  ]
}